home_stream/__init__.py
home_stream/app.py
home_stream/forms.py
home_stream/helpers.py
home_stream/static/favicon.png
home_stream/static/favicon.png.license
home_stream/static/main.js
home_stream/static/pico.min.css
home_stream/static/style.css
home_stream/templates/REUSE.toml
home_stream/templates/base.html
home_stream/templates/browse.html
home_stream/templates/login.html
home_stream/templates/play.html
home_stream/wsgi.py
home_stream-1.5.1.dist-info/METADATA
home_stream-1.5.1.dist-info/WHEEL
home_stream-1.5.1.dist-info/entry_points.txt
home_stream-1.5.1.dist-info/licenses/LICENSE
home_stream-1.5.1.dist-info/licenses/LICENSES/Apache-2.0.txt
home_stream-1.5.1.dist-info/licenses/LICENSES/CC0-1.0.txt
home_stream-1.5.1.dist-info/licenses/LICENSES/GPL-3.0-only.txt
home_stream-1.5.1.dist-info/licenses/LICENSES/MIT.txt
home_stream-1.5.1.dist-info/RECORD
