Metadata-Version: 2.4
Name: home-stream
Version: 1.5.1
Summary: Browser and streaming interface for local media files
License: GPL-3.0-only
License-File: LICENSE
License-File: LICENSES/Apache-2.0.txt
License-File: LICENSES/CC0-1.0.txt
License-File: LICENSES/GPL-3.0-only.txt
License-File: LICENSES/MIT.txt
Author: Max Mehl
Author-email: mail@mehl.mx
Requires-Python: >=3.10,<4.0
Classifier: License :: OSI Approved :: GNU General Public License v3 (GPLv3)
Classifier: Programming Language :: Python :: 3
Classifier: Programming Language :: Python :: 3.10
Classifier: Programming Language :: Python :: 3.11
Classifier: Programming Language :: Python :: 3.12
Classifier: Programming Language :: Python :: 3.13
Classifier: Programming Language :: Python :: 3.14
Requires-Dist: bcrypt (>=5.0.0,<6.0.0)
Requires-Dist: flask (>=3.1.2,<4.0.0)
Requires-Dist: flask-limiter[redis,valkey] (>=4.0.0,<5.0.0)
Requires-Dist: flask-wtf (>=1.2.2,<2.0.0)
Requires-Dist: pyyaml (>=6.0.3,<7.0.0)
Project-URL: Repository, https://github.com/mxmehl/home-stream
